flask_imagekitio/__init__.py
flask_imagekitio/py.typed
flask_imagekitio-0.1.3.dist-info/METADATA
flask_imagekitio-0.1.3.dist-info/WHEEL
flask_imagekitio-0.1.3.dist-info/top_level.txt
flask_imagekitio-0.1.3.dist-info/RECORD
